{
  "__inputs": [
    {
      "name": "DS_YESOREYERAM-INFINITY-DATASOURCE",
      "label": "yesoreyeram-infinity-datasource",
      "description": "",
      "type": "datasource",
      "pluginId": "yesoreyeram-infinity-datasource",
      "pluginName": "Infinity"
    },
    {
      "name": "DS_MYSQL-BEEFLOW",
      "label": "mysql-beeflow",
      "description": "",
      "type": "datasource",
      "pluginId": "mysql",
      "pluginName": "MySQL"
    }
  ],
  "__elements": {},
  "__requires": [
    {
      "type": "grafana",
      "id": "grafana",
      "name": "Grafana",
      "version": "11.6.0"
    },
    {
      "type": "datasource",
      "id": "mysql",
      "name": "MySQL",
      "version": "11.6.0-pre"
    },
    {
      "type": "panel",
      "id": "table",
      "name": "Table",
      "version": ""
    },
    {
      "type": "panel",
      "id": "text",
      "name": "Text",
      "version": ""
    },
    {
      "type": "panel",
      "id": "timeseries",
      "name": "Time series",
      "version": ""
    },
    {
      "type": "datasource",
      "id": "yesoreyeram-infinity-datasource",
      "name": "Infinity",
      "version": "3.1.0"
    }
  ],
  "annotations": {
    "list": [
      {
        "builtIn": 1,
        "datasource": {
          "type": "grafana",
          "uid": "-- Grafana --"
        },
        "enable": true,
        "hide": true,
        "iconColor": "rgba(0, 211, 255, 1)",
        "name": "Annotations & Alerts",
        "type": "dashboard"
      }
    ]
  },
  "description": "Desenvolvido por: Bee Solutions\nAutor: Fernando Almondes\nData: 24/03/2025 - 22:30",
  "editable": true,
  "fiscalYearStartMonth": 0,
  "graphTooltip": 0,
  "id": null,
  "links": [],
  "panels": [
    {
      "gridPos": {
        "h": 3,
        "w": 24,
        "x": 0,
        "y": 0
      },
      "id": 12,
      "options": {
        "code": {
          "language": "plaintext",
          "showLineNumbers": false,
          "showMiniMap": false
        },
        "content": "<div style=\"display: flex; align-items: center; justify-content: space-between; background-image: url('https://beesolutions.com.br/static/grafana/fundo-bee-05.jpg'); background-size: cover; padding: 20px 20px; border-radius: 8px; box-shadow: 0 4px 8px rgba(0, 0, 0, 0.2);\">\n    <div style=\"flex-shrink: 0;\">\n        <img src=\"https://beesolutions.com.br/static/home/images/bee/so-logo.png\" alt=\"Logo\" style=\"width: 60px; height: 50px;\">\n    </div>\n    <h2 style=\"flex-grow: 1; text-align: center; color: #ffffff; font-size: 24px; font-weight: bold; margin: 0;\">DASHBOARD BEEFLOW (STATS) - BEE</h2>\n    <div style=\" text-color: #ffffff; background-color: #ffffff; padding: 10px 20px; border-radius: 8px; box-shadow: 0 4px 8px rgba(0, 0, 0, 0.2); color: #333;\">\n        <a style=\"color: inherit; text-decoration: none;\" href=\"https://soft.beesolutions.com.br/\" target=\"new_blank\"> <p style=\"margin: 0;\">BEESOFT</p></a>\n    </div>\n</div>\n",
        "mode": "markdown"
      },
      "pluginVersion": "11.6.0",
      "transparent": true,
      "type": "text"
    },
    {
      "datasource": {
        "type": "yesoreyeram-infinity-datasource",
        "uid": "${DS_YESOREYERAM-INFINITY-DATASOURCE}"
      },
      "fieldConfig": {
        "defaults": {
          "color": {
            "mode": "thresholds"
          },
          "custom": {
            "align": "auto",
            "cellOptions": {
              "type": "color-background"
            },
            "filterable": true,
            "inspect": false
          },
          "mappings": [],
          "thresholds": {
            "mode": "absolute",
            "steps": [
              {
                "color": "#1e3d46"
              }
            ]
          }
        },
        "overrides": [
          {
            "matcher": {
              "id": "byName",
              "options": "bytes"
            },
            "properties": [
              {
                "id": "unit",
                "value": "decbytes"
              },
              {
                "id": "custom.cellOptions",
                "value": {
                  "type": "gauge"
                }
              },
              {
                "id": "thresholds",
                "value": {
                  "mode": "absolute",
                  "steps": [
                    {
                      "color": "dark-green"
                    },
                    {
                      "color": "dark-orange",
                      "value": 50000
                    },
                    {
                      "color": "dark-red",
                      "value": 100000
                    }
                  ]
                }
              }
            ]
          },
          {
            "matcher": {
              "id": "byName",
              "options": "bps"
            },
            "properties": [
              {
                "id": "unit",
                "value": "bps"
              },
              {
                "id": "custom.cellOptions",
                "value": {
                  "type": "gauge"
                }
              },
              {
                "id": "thresholds",
                "value": {
                  "mode": "absolute",
                  "steps": [
                    {
                      "color": "dark-green"
                    },
                    {
                      "color": "dark-orange",
                      "value": 50000010
                    },
                    {
                      "color": "dark-red",
                      "value": 100000000
                    }
                  ]
                }
              },
              {
                "id": "max",
                "value": 100000000
              }
            ]
          },
          {
            "matcher": {
              "id": "byName",
              "options": "packets"
            },
            "properties": []
          },
          {
            "matcher": {
              "id": "byName",
              "options": "pps"
            },
            "properties": [
              {
                "id": "unit",
                "value": "pps"
              }
            ]
          }
        ]
      },
      "gridPos": {
        "h": 13,
        "w": 24,
        "x": 0,
        "y": 3
      },
      "id": 6,
      "options": {
        "cellHeight": "sm",
        "footer": {
          "countRows": false,
          "enablePagination": true,
          "fields": "",
          "reducer": [
            "sum"
          ],
          "show": false
        },
        "showHeader": true,
        "sortBy": []
      },
      "pluginVersion": "11.6.0",
      "targets": [
        {
          "columns": [],
          "csv_options": {
            "delimiter": "",
            "skip_empty_lines": true,
            "skip_lines_with_error": true
          },
          "data": "firstSeen,lastSeen,proto,exporterID,engine,srcAddr,dstAddr,srcPort,dstPort,icmpTYpe,icmpCode,srcNet,dstNet,routerIP,srcAS,dstAS,packets,bytes,flags,tos,inSrcMac,outDstMac,inDstMac,outSrcMac,bps,pps,bpp,srcGeo,dstGeo,srcLocation,dstLocation,srcOrg,dstOrg\n2025-03-21 21:34:48.920,2025-03-21 21:34:48.920,6,1,0/0,214.235.80.3,192.168.237.152,1710,64,0,64,214.235.80.3/0,192.168.237.152/0,192.168.237.169,749,0,1,40,........,0,50:00:00:01:00:01,00:50:00:00:02:00,50:00:00:01:00:01,50:00:00:01:00:00,0,0,40,US,..,NA/US/'United States' long/lat: 37.7510/-97.8220,no location info,DNIC-AS-00749,\n2025-03-21 21:34:49.920,2025-03-21 21:34:49.920,6,1,0/0,16.126.145.240,192.168.237.152,1711,64,0,64,16.126.145.240/0,192.168.237.152/0,192.168.237.169,16509,0,1,40,........,0,50:00:00:01:00:01,00:50:00:00:02:00,50:00:00:01:00:01,50:00:00:01:00:00,0,0,40,US,..,NA/US/'United States' long/lat: 37.7510/-97.8220,no location info,AMAZON-02,\n2025-03-21 21:34:50.940,2025-03-21 21:34:50.940,6,1,0/0,44.11.115.128,192.168.237.152,1712,64,0,64,44.11.115.128/0,192.168.237.152/0,192.168.237.169,49268,0,1,40,........,0,50:00:00:01:00:01,00:50:00:00:02:00,50:00:00:01:00:01,50:00:00:01:00:00,0,0,40,BE,..,EU/BE/Belgium long/lat: 50.8509/4.3447,no location info,Hermes Telecom BVBA,\n2025-03-21 21:34:51.940,2025-03-21 21:34:51.940,6,1,0/0,125.236.250.224,192.168.237.152,1713,64,0,64,125.236.250.224/0,192.168.237.152/0,192.168.237.169,0,0,1,40,........,0,50:00:00:01:00:01,00:50:00:00:02:00,50:00:00:01:00:01,50:00:00:01:00:00,0,0,40,NZ,..,OC/NZ/Auckland long/lat: -36.8492/174.7889,no location info,,\n2025-03-21 21:34:52.960,2025-03-21 21:34:52.960,6,1,0/0,44.224.163.10,192.168.237.152,1714,64,0,64,44.224.163.10/0,192.168.237.152/0,192.168.237.169,16509,0,1,40,........,0,50:00:00:01:00:01,00:50:00:00:02:00,50:00:00:01:00:01,50:00:00:01:00:00,0,0,40,US,..,NA/US/Boardman long/lat: 45.8401/-119.7050,no location info,AMAZON-02,\n2025-03-21 21:34:53.960,2025-03-21 21:34:53.960,6,1,0/0,106.146.92.78,192.168.237.152,1715,64,0,64,106.146.92.78/0,192.168.237.152/0,192.168.237.169,2516,0,1,40,........,0,50:00:00:01:00:01,00:50:00:00:02:00,50:00:00:01:00:01,50:00:00:01:00:00,0,0,40,JP,..,AS/JP/Osaka long/lat: 34.6967/135.5154,no location info,KDDI CORPORATION,\n2025-03-21 21:34:54.920,2025-03-21 21:34:54.920,6,1,0/0,30.142.10.147,192.168.237.152,1716,64,0,64,30.142.10.147/0,192.168.237.152/0,192.168.237.169,749,0,1,40,........,0,50:00:00:01:00:01,00:50:00:00:02:00,50:00:00:01:00:01,50:00:00:01:00:00,0,0,40,US,..,NA/US/'United States' long/lat: 37.7510/-97.8220,no location info,DNIC-AS-00749,\n2025-03-21 21:34:55.920,2025-03-21 21:34:55.920,6,1,0/0,204.19.184.194,192.168.237.152,1717,64,0,64,204.19.184.194/0,192.168.237.152/0,192.168.237.169,0,0,1,40,........,0,50:00:00:01:00:01,00:50:00:00:02:00,50:00:00:01:00:01,50:00:00:01:00:00,0,0,40,CA,..,NA/CA/Canada long/lat: 43.6319/-79.3716,no location info,,\n2025-03-21 21:34:56.940,2025-03-21 21:34:56.940,6,1,0/0,199.144.244.204,192.168.237.152,1718,64,0,64,199.144.244.204/0,192.168.237.152/0,192.168.237.169,4152,0,1,40,........,0,50:00:00:01:00:01,00:50:00:00:02:00,50:00:00:01:00:01,50:00:00:01:00:00,0,0,40,US,..,NA/US/'United States' long/lat: 37.7510/-97.8220,no location info,USDA-1,\n2025-03-21 21:34:57.940,2025-03-21 21:34:57.940,6,1,0/0,171.222.9.31,192.168.237.152,1719,64,0,64,171.222.9.31/0,192.168.237.152/0,192.168.237.169,4134,0,1,40,........,0,50:00:00:01:00:01,00:50:00:00:02:00,50:00:00:01:00:01,50:00:00:01:00:00,0,0,40,CN,..,AS/CN/China long/lat: 34.7732/113.7220,no location info,Chinanet,",
          "datasource": {
            "type": "yesoreyeram-infinity-datasource",
            "uid": "${DS_YESOREYERAM-INFINITY-DATASOURCE}"
          },
          "filters": [],
          "format": "table",
          "global_query_id": "",
          "hide": false,
          "parser": "backend",
          "refId": "A",
          "root_selector": "",
          "source": "url",
          "type": "csv",
          "uql": "parse-csv",
          "url": "http://localhost:8000/api/nfdump3/?intervalo=${__from:date:YYYY/MM/DD/HH:mm:ss}-${__to:date:YYYY/MM/DD/HH:mm:ss}&filtro=$filtro&formato=json&ordenacao=$ordenacao&agregacao=$agregacao&flows=$flows&router=${host:raw}&token=$token",
          "url_options": {
            "data": "",
            "method": "GET"
          }
        }
      ],
      "title": "Flows - Agregado por: $agregacao",
      "transformations": [
        {
          "id": "organize",
          "options": {
            "excludeByName": {
              "dstContinente": true,
              "dstLatitude": true,
              "dstLocation": true,
              "dstLongitude": true,
              "srcContinente": true,
              "srcLatitude": true,
              "srcLocation": true,
              "srcLongitude": true
            },
            "includeByName": {},
            "indexByName": {
              "bps": 3,
              "duration": 6,
              "firstSeen": 1,
              "lastSeen": 5,
              "pps": 4,
              "proto": 7,
              "protocolo_nome": 2,
              "routerIP": 0
            },
            "renameByName": {}
          }
        }
      ],
      "transparent": true,
      "type": "table"
    },
    {
      "datasource": {
        "type": "yesoreyeram-infinity-datasource",
        "uid": "${DS_YESOREYERAM-INFINITY-DATASOURCE}"
      },
      "fieldConfig": {
        "defaults": {
          "color": {
            "mode": "palette-classic"
          },
          "custom": {
            "axisBorderShow": false,
            "axisCenteredZero": false,
            "axisColorMode": "text",
            "axisLabel": "",
            "axisPlacement": "auto",
            "barAlignment": 0,
            "barWidthFactor": 0.6,
            "drawStyle": "line",
            "fillOpacity": 50,
            "gradientMode": "hue",
            "hideFrom": {
              "legend": false,
              "tooltip": false,
              "viz": false
            },
            "insertNulls": false,
            "lineInterpolation": "linear",
            "lineWidth": 1,
            "pointSize": 5,
            "scaleDistribution": {
              "type": "linear"
            },
            "showPoints": "auto",
            "spanNulls": false,
            "stacking": {
              "group": "A",
              "mode": "none"
            },
            "thresholdsStyle": {
              "mode": "off"
            }
          },
          "mappings": [],
          "noValue": "Selecione um intervalo de até 1h ou use as Trends ;)",
          "thresholds": {
            "mode": "absolute",
            "steps": [
              {
                "color": "green"
              },
              {
                "color": "red",
                "value": 80
              }
            ]
          }
        },
        "overrides": [
          {
            "matcher": {
              "id": "byName",
              "options": "bps"
            },
            "properties": [
              {
                "id": "unit",
                "value": "bps"
              }
            ]
          },
          {
            "matcher": {
              "id": "byName",
              "options": "pps"
            },
            "properties": [
              {
                "id": "unit",
                "value": "pps"
              }
            ]
          },
          {
            "matcher": {
              "id": "byName",
              "options": "proto"
            },
            "properties": [
              {
                "id": "custom.hideFrom",
                "value": {
                  "legend": false,
                  "tooltip": false,
                  "viz": true
                }
              }
            ]
          }
        ]
      },
      "gridPos": {
        "h": 15,
        "w": 24,
        "x": 0,
        "y": 16
      },
      "id": 14,
      "options": {
        "legend": {
          "calcs": [
            "lastNotNull"
          ],
          "displayMode": "table",
          "placement": "bottom",
          "showLegend": true,
          "sortBy": "Last *",
          "sortDesc": true
        },
        "tooltip": {
          "hideZeros": false,
          "mode": "single",
          "sort": "none"
        }
      },
      "pluginVersion": "11.6.0",
      "targets": [
        {
          "columns": [],
          "computed_columns": [],
          "data": "",
          "datasource": {
            "type": "yesoreyeram-infinity-datasource",
            "uid": "${DS_YESOREYERAM-INFINITY-DATASOURCE}"
          },
          "filters": [],
          "format": "table",
          "global_query_id": "",
          "hide": false,
          "parser": "backend",
          "refId": "A",
          "root_selector": "$map($, function($v){{\n     \"timestamp\": $v.timestamp,\n     \"$unidade\": $v.$unidade,\n     \"${agregacao:text}\": $v.${agregacao:text},\n     \"src_ip\": \"${agregacao:text}\" = \"srcAddr\" ? $v.${agregacao:text} & \" (\" & $v.srcAS & \" - \" & $v.srcOrg & \")\",\n     \"src_ip4\": \"${agregacao:text}\" = \"srcip4\" ? $v.srcAddr & \"/24\" & \" (\" & $v.srcAS & \" - \" & $v.srcOrg & \")\",\n     \"src_ip6\": \"${agregacao:text}\" = \"srcip6\" ? $v.srcAddr & \"/32\" & \" (\" & $v.srcAS & \" - \" & $v.srcOrg & \")\",\n     \"dst_ip\": \"${agregacao:text}\" = \"dstAddr\" ? $v.${agregacao:text} & \" (\" & $v.dstAS & \" - \" & $v.dstOrg & \")\",\n     \"dst_ip4\": \"${agregacao:text}\" = \"dstip4\" ? $v.dstAddr & \"/24\" & \" (\" & $v.dstAS & \" - \" & $v.dstOrg & \")\",\n     \"dst_ip6\": \"${agregacao:text}\" = \"dstip6\" ? $v.dstAddr & \"/32\" & \" (\" & $v.dstAS & \" - \" & $v.dstOrg & \")\",\n     \"src_asn_nome\": \"${agregacao:text}\" = \"srcAS\" ? $v.srcOrg & \" (\" & \"AS\" & $v.${agregacao:text} & \")\",\n     \"dst_asn_nome\": \"${agregacao:text}\" = \"dstAS\" ? $v.dstOrg & \" (\" & \"AS\" & $v.${agregacao:text} & \")\",\n     \"protocolo_nome\": \"${agregacao:text}\" = \"proto\" ?  $v.${agregacao:text} & \" (\" & $v.protocolo_nome & \")\",\n     \"servico_nome\": \"${agregacao:text}\" = \"dstPort\" or \"${agregacao:text}\" = \"srcPort\" ? $v.${agregacao:text} & \" (\" & $v.servico_nome & \"/\" & $v.protocolo_nome & \")\",\n     \"router_ip\": \"${agregacao:text}\" = \"router\" ? $v.routerIP\n}})",
          "source": "url",
          "type": "json",
          "url": "http://localhost:8000/api/nfdump5/?intervalo=${__from:date:YYYY/MM/DD/HH:mm:ss}-${__to:date:YYYY/MM/DD/HH:mm:ss}&filtro=$filtro&agregacao=$agregacao&router=${host:raw}&token=$token",
          "url_options": {
            "data": "",
            "method": "GET"
          }
        }
      ],
      "title": "Tráfego por Agregação: $agregacao ($unidade)",
      "transformations": [
        {
          "id": "convertFieldType",
          "options": {
            "conversions": [
              {
                "destinationType": "time",
                "targetField": "timestamp"
              },
              {
                "destinationType": "number",
                "targetField": "bps"
              },
              {
                "destinationType": "number",
                "targetField": "pps"
              },
              {
                "destinationType": "other",
                "targetField": "proto"
              },
              {
                "destinationType": "other",
                "targetField": "srcAddr"
              },
              {
                "destinationType": "other",
                "targetField": "dstAddr"
              },
              {
                "destinationType": "other",
                "targetField": "srcPort"
              },
              {
                "destinationType": "other",
                "targetField": "dstPort"
              },
              {
                "destinationType": "other",
                "targetField": "srcAS"
              },
              {
                "destinationType": "other",
                "targetField": "dstAS"
              }
            ],
            "fields": {}
          }
        },
        {
          "id": "prepareTimeSeries",
          "options": {
            "format": "multi"
          }
        },
        {
          "id": "renameByRegex",
          "options": {
            "regex": "/bps |pps /",
            "renamePattern": ""
          }
        }
      ],
      "transparent": true,
      "type": "timeseries"
    }
  ],
  "refresh": "",
  "schemaVersion": 41,
  "tags": [
    "beesolutions",
    "beeflow",
    "netflow"
  ],
  "templating": {
    "list": [
      {
        "current": {},
        "datasource": {
          "type": "mysql",
          "uid": "${DS_MYSQL-BEEFLOW}"
        },
        "definition": "select distinct router from beeapi_flow;",
        "includeAll": true,
        "label": "Host",
        "multi": true,
        "name": "host",
        "options": [],
        "query": "select distinct router from beeapi_flow;",
        "refresh": 1,
        "regex": "",
        "type": "query"
      },
      {
        "current": {
          "text": "1000",
          "value": "1000"
        },
        "description": "",
        "label": "Flows",
        "name": "flows",
        "options": [
          {
            "selected": false,
            "text": "10",
            "value": "10"
          },
          {
            "selected": false,
            "text": "100",
            "value": "100"
          },
          {
            "selected": true,
            "text": "1000",
            "value": "1000"
          }
        ],
        "query": "10, 100, 1000",
        "type": "custom"
      },
      {
        "current": {
          "text": "router",
          "value": "router"
        },
        "label": "Agregação",
        "name": "agregacao",
        "options": [
          {
            "selected": false,
            "text": "srcAddr",
            "value": "srcip"
          },
          {
            "selected": false,
            "text": "dstAddr",
            "value": "dstip"
          },
          {
            "selected": false,
            "text": "srcPort",
            "value": "srcport"
          },
          {
            "selected": false,
            "text": "dstPort",
            "value": "dstport"
          },
          {
            "selected": false,
            "text": "srcAS",
            "value": "srcas"
          },
          {
            "selected": false,
            "text": "dstAS",
            "value": "dstas"
          },
          {
            "selected": false,
            "text": "proto",
            "value": "proto"
          },
          {
            "selected": true,
            "text": "router",
            "value": "router"
          },
          {
            "selected": false,
            "text": "srcip4",
            "value": "srcip4"
          },
          {
            "selected": false,
            "text": "dstip4",
            "value": "dstip4"
          },
          {
            "selected": false,
            "text": "srcip6",
            "value": "srcip6"
          },
          {
            "selected": false,
            "text": "dstip6",
            "value": "dstip6"
          }
        ],
        "query": "srcAddr : srcip, dstAddr : dstip, srcPort : srcport, dstPort : dstport, srcAS : srcas, dstAS : dstas, proto : proto, router : router, srcip4 : srcip4, dstip4 : dstip4, srcip6 : srcip6, dstip6 : dstip6",
        "type": "custom"
      },
      {
        "current": {
          "text": "flows",
          "value": "flows"
        },
        "label": "Ordenação",
        "name": "ordenacao",
        "options": [
          {
            "selected": false,
            "text": "bytes",
            "value": "bytes"
          },
          {
            "selected": false,
            "text": "packets",
            "value": "packets"
          },
          {
            "selected": true,
            "text": "flows",
            "value": "flows"
          }
        ],
        "query": "bytes,packets,flows",
        "type": "custom"
      },
      {
        "allowCustomValue": false,
        "current": {
          "text": "bps",
          "value": "bps"
        },
        "label": "Unidade",
        "name": "unidade",
        "options": [
          {
            "selected": true,
            "text": "bps",
            "value": "bps"
          },
          {
            "selected": false,
            "text": "pps",
            "value": "pps"
          }
        ],
        "query": "bps, pps",
        "type": "custom"
      },
      {
        "current": {
          "text": "any",
          "value": "any"
        },
        "label": "Filtro",
        "name": "filtro",
        "options": [
          {
            "selected": true,
            "text": "any",
            "value": "any"
          }
        ],
        "query": "any",
        "type": "custom"
      },
      {
        "allowCustomValue": false,
        "current": {
          "text": "68786e2c-2162-11f0-91fb-87ea6886144f",
          "value": "68786e2c-2162-11f0-91fb-87ea6886144f"
        },
        "hide": 2,
        "label": "Token",
        "name": "token",
        "options": [
          {
            "selected": true,
            "text": "68786e2c-2162-11f0-91fb-87ea6886144f",
            "value": "68786e2c-2162-11f0-91fb-87ea6886144f"
          }
        ],
        "query": "68786e2c-2162-11f0-91fb-87ea6886144f",
        "type": "custom"
      }
    ]
  },
  "time": {
    "from": "now-1h",
    "to": "now"
  },
  "timepicker": {},
  "timezone": "browser",
  "title": "Dashboard Beeflow (Stats) - BEE",
  "uid": "dehfxzgjsr9c0a",
  "version": 27,
  "weekStart": ""
}